ghobjects/__init__.py
ghobjects/devbranch.py
ghobjects/gitter.py
ghobjects/issue.py
ghobjects/lazyload.py
ghobjects/project.py
ghobjects-0.0.2.dist-info/licenses/LICENSE
ghobjects-0.0.2.dist-info/METADATA
ghobjects-0.0.2.dist-info/WHEEL
ghobjects-0.0.2.dist-info/top_level.txt
ghobjects-0.0.2.dist-info/RECORD
