Metadata-Version: 2.4
Name: GhObjects
Version: 0.0.2
Summary: GitHub entities made available as lazyload classes 
Home-page: https://github.com/thetechcollective/GhObjects
Author: Lars Kruse
Author-email: Lars Kruse <lars@lakruzz.com>
License-Expression: GPL-3.0-or-later
Keywords: github,trunk-based-development,automation
Classifier: Development Status :: 3 - Alpha
Classifier: Intended Audience :: Developers
Classifier: Natural Language :: English
Classifier: Programming Language :: Python :: 3
Classifier: Programming Language :: Python :: 3.13
Classifier: Operating System :: OS Independent
Requires-Python: >=3.12
License-File: LICENSE
Provides-Extra: dev
Requires-Dist: pytest; extra == "dev"
Requires-Dist: pytest-cov; extra == "dev"
Provides-Extra: build
Requires-Dist: setuptools; extra == "build"
Requires-Dist: packaging; extra == "build"
Dynamic: author
Dynamic: home-page
Dynamic: license-file
Dynamic: requires-python
